jpydict.py
jpydict-1.0.0.dist-info/DESCRIPTION.rst
jpydict-1.0.0.dist-info/METADATA
jpydict-1.0.0.dist-info/RECORD
jpydict-1.0.0.dist-info/WHEEL
jpydict-1.0.0.dist-info/entry_points.txt
jpydict-1.0.0.dist-info/metadata.json
jpydict-1.0.0.dist-info/top_level.txt
